cambrian/__init__.py
cambrian/_version.py
cambrian/config.py
cambrian/main.py
cambrian/agents/__init__.py
cambrian/agents/agent.py
cambrian/agents/object.py
cambrian/agents/point.py
cambrian/configs/__init__.py
cambrian/configs/base.yaml
cambrian/configs/env/env.yaml
cambrian/configs/env/maze_env.yaml
cambrian/configs/env/agents/agent.yaml
cambrian/configs/env/agents/object.yaml
cambrian/configs/env/agents/object_sphere.yaml
cambrian/configs/env/agents/object_sphere_light.yaml
cambrian/configs/env/agents/object_sphere_textured.yaml
cambrian/configs/env/agents/object_sphere_textured_adversary.yaml
cambrian/configs/env/agents/object_sphere_textured_goal.yaml
cambrian/configs/env/agents/point.yaml
cambrian/configs/env/agents/point_seeker.yaml
cambrian/configs/env/agents/point_seeker_maze.yaml
cambrian/configs/env/agents/point_seeker_random.yaml
cambrian/configs/env/agents/point_textured.yaml
cambrian/configs/env/agents/eyes/eye.yaml
cambrian/configs/env/agents/eyes/multi_eye.yaml
cambrian/configs/env/agents/eyes/optics.yaml
cambrian/configs/env/agents/eyes/aperture/aperture.yaml
cambrian/configs/env/agents/eyes/aperture/circular.yaml
cambrian/configs/env/agents/eyes/aperture/mask.yaml
cambrian/configs/env/agents/eyes/aperture/random_mask.yaml
cambrian/configs/env/mazes/ALL.yaml
cambrian/configs/env/mazes/COMPLEX.yaml
cambrian/configs/env/mazes/COMPLEX_LARGE.yaml
cambrian/configs/env/mazes/L.yaml
cambrian/configs/env/mazes/OPEN.yaml
cambrian/configs/env/mazes/OPEN_LARGE.yaml
cambrian/configs/env/mazes/STRAIGHT.yaml
cambrian/configs/env/mazes/Y.yaml
cambrian/configs/env/mazes/maze.yaml
cambrian/configs/env/renderer/bev.yaml
cambrian/configs/env/renderer/bev_tracking.yaml
cambrian/configs/env/renderer/fixed.yaml
cambrian/configs/env/renderer/renderer.yaml
cambrian/configs/env/renderer/tracking.yaml
cambrian/configs/evo/all.yaml
cambrian/configs/evo/evo.yaml
cambrian/configs/evo/constraints/morphological_feasibility_small.yaml
cambrian_core-0.0.0.dist-info/LICENSE
cambrian_core-0.0.0.dist-info/METADATA
cambrian_core-0.0.0.dist-info/WHEEL
cambrian_core-0.0.0.dist-info/top_level.txt
cambrian_core-0.0.0.dist-info/RECORD
