Metadata-Version: 2.2
Name: cambrian-core
Version: 0.0.0
Summary: Artificial Cambrian Intelligence
Requires-Python: >=3.11
License-File: LICENSE
Requires-Dist: stable_baselines3[extra]>=2.4.0
Requires-Dist: pettingzoo>=1.24.3
Requires-Dist: mujoco[usd]>=3.2.5
Requires-Dist: mujoco-mjx>=3.2.6
Requires-Dist: brax>=0.12.1
Requires-Dist: jax>=0.4.38
Requires-Dist: pyyaml>=6.0.2
Requires-Dist: scipy>=1.14.1
Requires-Dist: scikit-image>=0.24.0
Requires-Dist: imageio>=2.36.0
Requires-Dist: opencv-python>=4.10.0.84
Requires-Dist: fcmaes>=1.6.11
Requires-Dist: tqdm>=4.67.0
Requires-Dist: nevergrad>=1.0.3
Requires-Dist: bayesian-optimization>=1.4.0
Requires-Dist: hydra-config>=0.0.10
Requires-Dist: hydra-nevergrad-sweeper>=1.2.0
Requires-Dist: hydra-submitit-launcher>=1.2.0
Requires-Dist: hydra-joblib-launcher>=1.2.0
Provides-Extra: dev
Requires-Dist: black>=24.8.0; extra == "dev"
Requires-Dist: flake8>=7.1.1; extra == "dev"
Requires-Dist: Flake8-pyproject>=1.2.3; extra == "dev"
Requires-Dist: isort>=5.13.2; extra == "dev"
Requires-Dist: pyright>=1.1.381; extra == "dev"
Requires-Dist: pytest>=8.3.3; extra == "dev"
Requires-Dist: pre-commit>=3.8.0; extra == "dev"
Provides-Extra: docs
Requires-Dist: sphinx>=7.2.6; extra == "docs"
Requires-Dist: furo>=2024.8.6; extra == "docs"
Requires-Dist: sphinx-autoapi>=3.4.0; extra == "docs"
Requires-Dist: sphinx-autobuild>=2024.10.3; extra == "docs"
Requires-Dist: sphinx-copybutton>=0.5.2; extra == "docs"
Requires-Dist: myst-parser>=4.0.0; extra == "docs"
Requires-Dist: sphinxcontrib-video>=0.3.1; extra == "docs"
Requires-Dist: sphinxcontrib-googleanalytics>=0.4; extra == "docs"
Requires-Dist: sphinx_design>=0.6.1; extra == "docs"
